csodium/__init__.py
csodium/_build.py
csodium/_impl.abi3.so
csodium-0.0.3.dist-info/DESCRIPTION.rst
csodium-0.0.3.dist-info/METADATA
csodium-0.0.3.dist-info/RECORD
csodium-0.0.3.dist-info/WHEEL
csodium-0.0.3.dist-info/metadata.json
csodium-0.0.3.dist-info/top_level.txt
